<?xml version="1.0" encoding="UTF-8"?>
<!DOCTYPE suite SYSTEM "http://testng.org/testng-1.0.dtd">

<suite name="Master Suite">

    <listeners>
        <listener class-name="utilities.ExtentReportManager"/>
        <listener class-name="app.getxray.xray.testng.listeners.XrayListener" />
    </listeners>

    <test name="Test">
        <parameter name="browser" value="chrome"/>
        <parameter name="os" value="Windows"/>

        <classes>
           <!-- <class name="testCases.RegistrationTest"/>
            <class name="testCases.LoginTest"/>-->
            <!-- <class name="testCases.CreateClassTest"/>
             <class name="testCases.EditClassTest"/>
             <class name="testCases.DeleteClassTest"/>
             <class name="testCases.ImportStudentsTest"/>-->
            <!-- <class name="testCases.AbsenceAlertTest"/>-->
            <class name="testCases.LoginDDT"/>
            <class name="testCases.CreateClassDDT"/>
        </classes>
    </test>
</suite>